<ns0:Lab xmlns:ns0="http://indivo.org/vocab/xml/documents#">
   <ns0:dateMeasured>2010-06-07T00:00:00Z</ns0:dateMeasured>
   <ns0:labType>PTT (Partial Thromboplastin)</ns0:labType>
   <ns0:laboratory>
      <ns0:name>Hematology</ns0:name>
      <ns0:address>Children's Hospital Boston</ns0:address>
   </ns0:laboratory>
   <ns0:labTest xmlns:xsi="http://www.w3.org/2001/XMLSchema-instance" xsi:type="ns0:SingleResultLabTest">
      <ns0:dateMeasured>2010-06-07T00:00:00Z</ns0:dateMeasured>
      <ns0:name abbrev="PTT (Partial Thromboplastin)">PTT (Partial Thromboplastin)</ns0:name>
      <ns0:final>true</ns0:final>
      <ns0:result xsi:type="ns0:ResultInRange">
         <ns0:flag abbrev="L" type="http://indivohealth.org/codes/hl7-abnormal-flags#" value="L">Low</ns0:flag>
         <ns0:valueAndUnit>
            <ns0:value>21.3</ns0:value>
            <ns0:unit abbrev="sec" type="http://indivohealth.org/codes/units#" value="sec">sec</ns0:unit>
         </ns0:valueAndUnit>
         <ns0:normalRange>
            <ns0:minimum>24.0</ns0:minimum>
            <ns0:maximum>32.0</ns0:maximum>
            <ns0:unit abbrev="sec" type="http://indivohealth.org/codes/units#" value="sec">sec</ns0:unit>
         </ns0:normalRange>
      </ns0:result>
   </ns0:labTest>
</ns0:Lab>