<ns0:Lab xmlns:ns0="http://indivo.org/vocab/xml/documents#">
   <ns0:dateMeasured>2010-03-05T00:00:00Z</ns0:dateMeasured>
   <ns0:labType>Hemoglobin Electrophoresis</ns0:labType>
   <ns0:laboratory>
      <ns0:name>Lab Control</ns0:name>
      <ns0:address>Children's Hospital Boston</ns0:address>
   </ns0:laboratory>
   <ns0:labPanel>
      <ns0:name>Hemoglobin Electrophoresis</ns0:name>
      <ns0:labTest xmlns:xsi="http://www.w3.org/2001/XMLSchema-instance" xsi:type="ns0:SingleResultLabTest">
         <ns0:dateMeasured>2010-03-12T00:00:00Z</ns0:dateMeasured>
         <ns0:name abbrev="Hgb A1, Hgb Electrophoresis">Hgb A1, Hgb Electrophoresis</ns0:name>
         <ns0:final>true</ns0:final>
         <ns0:result xsi:type="ns0:ResultInRange">
            <ns0:flag abbrev="L" type="http://indivohealth.org/codes/hl7-abnormal-flags#" value="L">Low</ns0:flag>
            <ns0:valueAndUnit>
               <ns0:value>0.0</ns0:value>
               <ns0:unit abbrev="%" type="http://indivohealth.org/codes/units#" value="%">%</ns0:unit>
            </ns0:valueAndUnit>
         </ns0:result>
      </ns0:labTest>
      <ns0:labTest xmlns:xsi="http://www.w3.org/2001/XMLSchema-instance" xsi:type="ns0:SingleResultLabTest">
         <ns0:dateMeasured>2010-03-12T00:00:00Z</ns0:dateMeasured>
         <ns0:name abbrev="Hgb A2, Hgb Electrophoresis">Hgb A2, Hgb Electrophoresis</ns0:name>
         <ns0:final>true</ns0:final>
         <ns0:result xsi:type="ns0:ResultInRange">
            <ns0:flag abbrev="H" type="http://indivohealth.org/codes/hl7-abnormal-flags#" value="H">High</ns0:flag>
            <ns0:valueAndUnit>
               <ns0:value>4.1</ns0:value>
               <ns0:unit abbrev="%" type="http://indivohealth.org/codes/units#" value="%">%</ns0:unit>
            </ns0:valueAndUnit>
         </ns0:result>
      </ns0:labTest>
      <ns0:labTest xmlns:xsi="http://www.w3.org/2001/XMLSchema-instance" xsi:type="ns0:SingleResultLabTest">
         <ns0:dateMeasured>2010-03-12T00:00:00Z</ns0:dateMeasured>
         <ns0:name abbrev="Hgb F, Hgb Electrophoresis">Hgb F, Hgb Electrophoresis</ns0:name>
         <ns0:final>true</ns0:final>
         <ns0:result xsi:type="ns0:ResultInRange">
            <ns0:flag abbrev="H" type="http://indivohealth.org/codes/hl7-abnormal-flags#" value="H">High</ns0:flag>
            <ns0:valueAndUnit>
               <ns0:value>6.9</ns0:value>
               <ns0:unit abbrev="%" type="http://indivohealth.org/codes/units#" value="%">%</ns0:unit>
            </ns0:valueAndUnit>
         </ns0:result>
      </ns0:labTest>
      <ns0:labTest xmlns:xsi="http://www.w3.org/2001/XMLSchema-instance" xsi:type="ns0:SingleResultLabTest">
         <ns0:dateMeasured>2010-03-12T00:00:00Z</ns0:dateMeasured>
         <ns0:name abbrev="Hgb S, Hgb Electrophoresis">Hgb S, Hgb Electrophoresis</ns0:name>
         <ns0:final>true</ns0:final>
         <ns0:result xsi:type="ns0:ResultInRange">
            <ns0:flag abbrev="H" type="http://indivohealth.org/codes/hl7-abnormal-flags#" value="H">High</ns0:flag>
            <ns0:valueAndUnit>
               <ns0:value>83.6</ns0:value>
               <ns0:unit abbrev="%" type="http://indivohealth.org/codes/units#" value="%">%</ns0:unit>
            </ns0:valueAndUnit>
         </ns0:result>
      </ns0:labTest>
      <ns0:labTest xmlns:xsi="http://www.w3.org/2001/XMLSchema-instance" xsi:type="ns0:SingleResultLabTest">
         <ns0:dateMeasured>2010-03-12T00:00:00Z</ns0:dateMeasured>
         <ns0:name abbrev="Hgb C, Hgb Electrophoresis">Hgb C, Hgb Electrophoresis</ns0:name>
         <ns0:final>true</ns0:final>
         <ns0:result xsi:type="ns0:ResultInRange">
            <ns0:valueAndUnit>
               <ns0:value>0.0</ns0:value>
               <ns0:unit abbrev="%" type="http://indivohealth.org/codes/units#" value="%">%</ns0:unit>
            </ns0:valueAndUnit>
         </ns0:result>
      </ns0:labTest>
      <ns0:labTest xmlns:xsi="http://www.w3.org/2001/XMLSchema-instance" xsi:type="ns0:SingleResultLabTest">
         <ns0:dateMeasured>2010-03-12T00:00:00Z</ns0:dateMeasured>
         <ns0:name abbrev="Hgb E, Hgb Electrophoresis">Hgb E, Hgb Electrophoresis</ns0:name>
         <ns0:final>true</ns0:final>
         <ns0:result xsi:type="ns0:ResultInRange">
            <ns0:valueAndUnit>
               <ns0:value>0.0</ns0:value>
               <ns0:unit abbrev="%" type="http://indivohealth.org/codes/units#" value="%">%</ns0:unit>
            </ns0:valueAndUnit>
         </ns0:result>
      </ns0:labTest>
      <ns0:labTest xmlns:xsi="http://www.w3.org/2001/XMLSchema-instance" xsi:type="ns0:SingleResultLabTest">
         <ns0:dateMeasured>2010-03-12T00:00:00Z</ns0:dateMeasured>
         <ns0:name abbrev="Hgb Other, Hgb Electrophoresis">Hgb Other, Hgb Electrophoresis</ns0:name>
         <ns0:final>true</ns0:final>
         <ns0:result xsi:type="ns0:ResultInRange">
            <ns0:flag abbrev="H" type="http://indivohealth.org/codes/hl7-abnormal-flags#" value="H">High</ns0:flag>
            <ns0:valueAndUnit>
               <ns0:value>5.4</ns0:value>
               <ns0:unit abbrev="%" type="http://indivohealth.org/codes/units#" value="%">%</ns0:unit>
            </ns0:valueAndUnit>
         </ns0:result>
      </ns0:labTest>
      <ns0:labTest xmlns:xsi="http://www.w3.org/2001/XMLSchema-instance" xsi:type="ns0:SingleResultLabTest">
         <ns0:dateMeasured>2010-03-12T00:00:00Z</ns0:dateMeasured>
         <ns0:name abbrev="Hgb Abn, Hgb Electrophoresis">Hgb Abn, Hgb Electrophoresis</ns0:name>
         <ns0:final>true</ns0:final>
         <ns0:result xsi:type="ns0:ResultInRange">
            <ns0:valueAndUnit>
               <ns0:textValue>Abnormal</ns0:textValue>
            </ns0:valueAndUnit>
         </ns0:result>
      </ns0:labTest>
      <ns0:labTest xmlns:xsi="http://www.w3.org/2001/XMLSchema-instance" xsi:type="ns0:SingleResultLabTest">
         <ns0:dateMeasured>2010-03-12T00:00:00Z</ns0:dateMeasured>
         <ns0:name abbrev="Acid Hgb Elect Conf">Acid Hgb Elect Conf</ns0:name>
         <ns0:final>true</ns0:final>
         <ns0:result xsi:type="ns0:ResultInRange">
            <ns0:valueAndUnit>
               <ns0:textValue>Not Appl</ns0:textValue>
            </ns0:valueAndUnit>
         </ns0:result>
      </ns0:labTest>
      <ns0:labTest xmlns:xsi="http://www.w3.org/2001/XMLSchema-instance" xsi:type="ns0:SingleResultLabTest">
         <ns0:dateMeasured>2010-03-12T00:00:00Z</ns0:dateMeasured>
         <ns0:name abbrev="Alkaline Hgb Elect Conf">Alkaline Hgb Elect Conf</ns0:name>
         <ns0:final>true</ns0:final>
         <ns0:result xsi:type="ns0:ResultInRange">
            <ns0:valueAndUnit>
               <ns0:textValue>Not Appl</ns0:textValue>
            </ns0:valueAndUnit>
         </ns0:result>
      </ns0:labTest>
      <ns0:labTest xmlns:xsi="http://www.w3.org/2001/XMLSchema-instance" xsi:type="ns0:SingleResultLabTest">
         <ns0:dateMeasured>2010-03-12T00:00:00Z</ns0:dateMeasured>
         <ns0:name abbrev="Sickle Cell Solubility Conf">Sickle Cell Solubility Conf</ns0:name>
         <ns0:final>true</ns0:final>
         <ns0:result xsi:type="ns0:ResultInRange">
            <ns0:valueAndUnit>
               <ns0:textValue>Performe</ns0:textValue>
            </ns0:valueAndUnit>
         </ns0:result>
      </ns0:labTest>
      <ns0:labTest xmlns:xsi="http://www.w3.org/2001/XMLSchema-instance" xsi:type="ns0:SingleResultLabTest">
         <ns0:dateMeasured>2010-03-12T00:00:00Z</ns0:dateMeasured>
         <ns0:name abbrev="Interpretation, Hgb Electrophoresis">Interpretation, Hgb Electrophoresis</ns0:name>
         <ns0:final>true</ns0:final>
      <ns0:result xsi:type="ns0:ResultInSet"><ns0:value>unknown</ns0:value></ns0:result></ns0:labTest>
      <ns0:labTest xmlns:xsi="http://www.w3.org/2001/XMLSchema-instance" xsi:type="ns0:SingleResultLabTest">
         <ns0:dateMeasured>2010-03-12T00:00:00Z</ns0:dateMeasured>
         <ns0:name abbrev="Interpretation, Hgb Electrophoresis">Interpretation, Hgb Electrophoresis</ns0:name>
         <ns0:final>true</ns0:final>
      <ns0:result xsi:type="ns0:ResultInSet"><ns0:value>unknown</ns0:value></ns0:result></ns0:labTest>
   </ns0:labPanel>
   <ns0:comments>--</ns0:comments>
</ns0:Lab>